attp_core-0.2.4.dist-info/METADATA
attp_core-0.2.4.dist-info/WHEEL
attp_core-0.2.4.dist-info/licenses/LICENSE
attp_core/rs_api.cpython-311-x86_64-linux-gnu.so
attp_core/rs_api.pyi
attp_core-0.2.4.dist-info/RECORD
