Metadata-Version: 2.4
Name: attp_core
Version: 0.2.4
Classifier: Programming Language :: Python
License-File: LICENSE
License-Expression: LICENSE
